tensorlearn/__init__.py
tensorlearn/tl_methods.py
tensorlearn/decomposition/__init__.py
tensorlearn/decomposition/candecomp_parafac.py
tensorlearn/decomposition/factorization.py
tensorlearn/decomposition/tensor_train.py
tensorlearn/decomposition/tucker.py
tensorlearn/operations/__init__.py
tensorlearn/operations/matrix_operations.py
tensorlearn/operations/tensor_operations.py
tensorlearn/shape_search/__init__.py
tensorlearn/shape_search/ga_shape_search.py
tensorlearn/shape_search/random_shapes.py
tensorlearn/shape_search/tensor_shape_search.py
tensorlearn/tensor_completion/__init__.py
tensorlearn/tensor_completion/cp_completion.py
tensorlearn/tensor_geometry/__init__.py
tensorlearn/tensor_geometry/nn_tensor_geometry_optimization.py
tensorlearn/tensor_geometry/tensor_geometry_graph.py
tensorlearn/tensor_geometry/utils.py
tensorlearn-1.1.24.dist-info/LICENSE
tensorlearn-1.1.24.dist-info/METADATA
tensorlearn-1.1.24.dist-info/WHEEL
tensorlearn-1.1.24.dist-info/top_level.txt
tensorlearn-1.1.24.dist-info/RECORD
