Metadata-Version: 2.1
Name: tensorlearn
Version: 1.1.24
Summary: A Python Package for Advanced Tensor Learning Methods
Home-page: https://github.com/rmsolgi/tensorlearn.git
Author: Ryan Solgi
Author-email: ryan.solgi@gmail.com
Maintainer: Ryan Solgi
Keywords: tensor,decomposition,tensor-train,rank,auto-rank,CANDECOMP,PARAFAC,CP
Classifier: Programming Language :: Python :: 3
Classifier: License :: OSI Approved :: MIT License
Classifier: Operating System :: OS Independent
Classifier: Topic :: Software Development :: Libraries :: Python Modules
License-File: LICENSE
Requires-Dist: numpy
